pjdev_message_broker/__about__.py
pjdev_message_broker/__init__.py
pjdev_message_broker/models.py
pjdev_message_broker/nats_service.py
pjdev_message_broker/py.typed
pjdev_message_broker-4.6.3.dist-info/METADATA
pjdev_message_broker-4.6.3.dist-info/WHEEL
pjdev_message_broker-4.6.3.dist-info/licenses/LICENSE.txt
pjdev_message_broker-4.6.3.dist-info/RECORD
